mb_pipedrive_integration/__init__.py
mb_pipedrive_integration/dataclasses.py
mb_pipedrive_integration/exceptions.py
mb_pipedrive_integration/new.py
mb_pipedrive_integration/services.py
mb_pipedrive_integration-1.2.2.dist-info/METADATA
mb_pipedrive_integration-1.2.2.dist-info/WHEEL
mb_pipedrive_integration-1.2.2.dist-info/licenses/LICENSE
mb_pipedrive_integration-1.2.2.dist-info/RECORD
